chatlite/__init__.py
chatlite/app.py
chatlite/core/__init__.py
chatlite/core/_hf_type.py
chatlite/core/chat_service.py
chatlite/core/config.py
chatlite/core/features/__init__.py
chatlite/core/features/base.py
chatlite/core/features/basic_google.py
chatlite/core/features/llm_search.py
chatlite/core/features/rawwebsearch_agent.py
chatlite/core/features/websearch_agent.py
chatlite/core/model_names.py
chatlite/core/model_service.py
chatlite/core/server.py
chatlite/runner.py
complexity_runner.py
chatlite-0.1.13.dist-info/METADATA
chatlite-0.1.13.dist-info/WHEEL
chatlite-0.1.13.dist-info/entry_points.txt
chatlite-0.1.13.dist-info/RECORD
