Metadata-Version: 2.1
Name: chatlite
Version: 0.1.13
Summary: ai powered chatapp for browsing and search
Home-page: https://github.com/santhosh/
License: MIT
Author: Kammari Santhosh
Requires-Python: >=3.10,<4.0
Classifier: License :: OSI Approved :: MIT License
Classifier: Programming Language :: Python :: 3
Classifier: Programming Language :: Python :: 3.10
Classifier: Programming Language :: Python :: 3.11
Classifier: Programming Language :: Python :: 3.12
Classifier: Programming Language :: Python :: 3.13
Requires-Dist: fastapi (>=0.115.6,<0.116.0)
Requires-Dist: openai (>=1.58.1,<2.0.0)
Requires-Dist: tenacity (>=9.0.0,<10.0.0)
Project-URL: Repository, https://github.com/santhosh/
